pathways_bench/__init__.py
pathways_bench/logger.py
pathways_bench/tessellate.py
pathways_bench/version.py
pathways_bench-0.0.1.dist-info/LICENSE
pathways_bench-0.0.1.dist-info/METADATA
pathways_bench-0.0.1.dist-info/WHEEL
pathways_bench-0.0.1.dist-info/top_level.txt
pathways_bench-0.0.1.dist-info/RECORD
