Metadata-Version: 2.1
Name: pathways-bench
Version: 0.0.1
Summary: A Benchmark for Extracting Routable Pedestrian Path Network Graphs
Home-page: https://github.com/TaskarCenterAtUW/pathways-bench
Author: Sujata Misra
Author-email: sujatam@gaussiansolutions.com
Project-URL: Documentation, https://github.com/TaskarCenterAtUW/pathways-bench/blob/main/README.md
Project-URL: GitHub, https://github.com/TaskarCenterAtUW/pathways-bench.git
Project-URL: Changelog, https://github.com/TaskarCenterAtUW/pathways-bench/blob/main/CHANGELOG.md
Classifier: Programming Language :: Python :: 3
Classifier: License :: OSI Approved :: MIT License
Classifier: Operating System :: OS Independent
Requires-Python: >=3.10
License-File: LICENSE
Requires-Dist: geopandas==0.14.3
Requires-Dist: osmnx==1.6.0
Requires-Dist: geonetworkx==0.5.3
Requires-Dist: networkx==3.2.1
Requires-Dist: shapely==2.0.3
Requires-Dist: fiona==1.9.6
